migro/__init__.py
migro/database.py
migro/dbt.py
migro/jinja.py
migro/main.py
migro/migrations.py
tests/__init__.py
tests/conftest.py
tests/test_database.py
tests/test_dbt.py
tests/test_jinja.py
tests/test_main.py
tests/test_migrations.py
migro-0.4.0.dist-info/LICENSE
migro-0.4.0.dist-info/METADATA
migro-0.4.0.dist-info/WHEEL
migro-0.4.0.dist-info/entry_points.txt
migro-0.4.0.dist-info/top_level.txt
migro-0.4.0.dist-info/RECORD
