Metadata-Version: 2.1
Name: migro
Version: 0.4.0
Summary: Data Warehouse migrations for dbt.
Home-page: https://github.com/troyharvey/migro
Author: Troy Harvey
Author-email: Troy Harvey <troyharvey@gmail.com>
License: MIT License
Project-URL: Homepage, https://github.com/troyharvey/migro
Project-URL: Bug Tracker, https://github.com/troyharvey/migro/issues
Requires-Python: >=3.10
License-File: LICENSE
Requires-Dist: Click >=8.1.0
Requires-Dist: Jinja2 >=3.1.0
Requires-Dist: psycopg2 >=2.9.1
Requires-Dist: pyyaml >=6.0.1
Requires-Dist: snowflake-connector-python >=3.10.0
Requires-Dist: sqlparse >=0.5.0
Provides-Extra: dev
Requires-Dist: pytest-cov >=5.0.0 ; extra == 'dev'
Requires-Dist: pytest >=8.2.1 ; extra == 'dev'
Requires-Dist: ruff >=0.4.4 ; extra == 'dev'
Requires-Dist: twine >=5.1.0 ; extra == 'dev'
